{"cameraMode":{"drawMode":0,"name":"Shaded","section":"Shading Mode"},"sceneLighting":false,"audioPlay":false,"sceneViewState":{"m_AlwaysRefresh":false,"showFog":true,"showSkybox":false,"showFlares":true,"showImageEffects":true,"showParticleSystems":true,"showVisualEffectGraphs":true,"m_FxEnabled":true},"in2DMode":false,"pivot":{"x":2.1136183738708498,"y":-0.4783861041069031,"z":-9.420446395874024},"rotation":{"x":-0.06625983119010925,"y":0.9328296780586243,"z":-0.27088505029678347,"w":-0.2282993644475937},"size":1.7320507764816285,"orthographic":false}